<bill session="111" type="h" number="107" updated="2009-01-14T08:31:49-05:00">
	<status><introduced date="1231218000" datetime="2009-01-06"/></status>

	<introduced date="1231218000" datetime="2009-01-06"/>
	<titles>
		<title type="short" as="introduced">Securing Medicare and Retirement for Tomorrow Act of 2009</title>
		<title type="short" as="introduced">SMART Act of 2009</title>
		<title type="official" as="introduced">To reform Social Security retirement and Medicare by establishing a Personal Social Security Savings Program to create a safer, healthier, more secure, and more prosperous retirement for all Americans and to reduce the burden on young Americans.</title>
	</titles>
	<sponsor id="400134"/>
	<cosponsors>
		<cosponsor id="400199" joined="2009-01-06"/>
		<cosponsor id="400643" joined="2009-01-06"/>
	</cosponsors>
	<actions>
		<action date="1231218000" datetime="2009-01-06"><text>Referred to the Committee on Ways and Means, and in addition to the Committees on Education and Labor, the Budget, Energy and Commerce, and Rules, for a period to be subsequently determined by the Speaker, in each case for consideration of such provisions as fall within the jurisdiction of the committee concerned.</text></action>
		<action date="1231218000" datetime="2009-01-06"><text>Referred to House Ways and Means</text></action>
		<action date="1231218000" datetime="2009-01-06"><text>Referred to House Education and Labor</text></action>
		<action date="1231218000" datetime="2009-01-06"><text>Referred to House Budget</text></action>
		<action date="1231218000" datetime="2009-01-06"><text>Referred to House Energy and Commerce</text></action>
		<action date="1231218000" datetime="2009-01-06"><text>Referred to House Rules</text></action>
	</actions>
	<committees>
		<committee name="House Ways and Means" subcommittee="" activity="Referral, In Committee" />
		<committee name="House Education and Labor" subcommittee="" activity="Referral, In Committee" />
		<committee name="House Budget" subcommittee="" activity="Referral, In Committee" />
		<committee name="House Energy and Commerce" subcommittee="" activity="Referral, In Committee" />
		<committee name="House Rules" subcommittee="" activity="Referral, In Committee" />
	</committees>
	<relatedbills>

	</relatedbills>
	<subjects>

	</subjects>
	<amendments>

	</amendments>
	<summary>
	
	</summary>
</bill>
