<bill session="111" type="h" number="538" updated="2009-01-15T12:09:29-05:00">
	<status><introduced date="1231909200" datetime="2009-01-14"/></status>

	<introduced date="1231909200" datetime="2009-01-14"/>
	<titles>
		<title type="official" as="introduced">To amend the Internal Revenue Code of 1986 to reduce the earned income threshold applicable to the refundable portion of the child tax credit and to increase the age limit for such credit.</title>
	</titles>
	<sponsor id="400309"/>
	<cosponsors>
		<cosponsor id="400645" joined="2009-01-14"/>
	</cosponsors>
	<actions>
		<action date="1231909200" datetime="2009-01-14"><text>Referred to the House Committee on Ways and Means.</text></action>
	</actions>
	<committees>
		<committee name="House Ways and Means" subcommittee="" activity="Referral, In Committee" />
	</committees>
	<relatedbills>

	</relatedbills>
	<subjects>

	</subjects>
	<amendments>

	</amendments>
	<summary>
	
	</summary>
</bill>
